fuzzix/__init__.py
fuzzix/fuzzix.py
fuzzix-0.0.1.data/scripts/fuzzixscan
fuzzix-0.0.1.dist-info/METADATA
fuzzix-0.0.1.dist-info/RECORD
fuzzix-0.0.1.dist-info/WHEEL
fuzzix-0.0.1.dist-info/top_level.txt
