Metadata-Version: 2.1
Name: fuzzix
Version: 0.0.1
Summary: a python-driven url fuzzer and web-spiderer with the aim to give you a as detailed as possible insight of the websites' structure
Home-page: https://github.com/cybertschunk/fuzzix
Author: David Leeuwestein
Author-email: cybertschunk@mailbox.org
License: GNU General Public License v3
Keywords: fuzzix
Platform: UNKNOWN
Classifier: Development Status :: 2 - Pre-Alpha
Classifier: Intended Audience :: Developers
Classifier: License :: OSI Approved :: GNU General Public License v3 (GPLv3)
Classifier: Natural Language :: English
Classifier: Programming Language :: Python :: 3.5
Classifier: Programming Language :: Python :: 3.6
Requires-Dist: beautifulsoup4
Requires-Dist: colorama
Requires-Dist: coloredlogger
Requires-Dist: urllib3
